{
  "module": "M0.0",
  "scenarios": [
    "SMOKE-1 — scripts/sync-specs.sh est exécutable"
  ],
  "deliverables": [
    {
      "id": "M0.0-01",
      "ref_cdc": "specs/cdc/01 - Cahier des charges App/07 - Architecture technique.md",
      "artefact": null,
      "test": "SMOKE-1 — scripts/sync-specs.sh est exécutable",
      "statut": "implemented",
      "libelle": "SMOKE-1 — scripts/sync-specs.sh est exécutable"
    }
  ],
  "cdc_source_hash": {
    "specs/cdc/01 - Cahier des charges App/07 - Architecture technique.md": "7fd998b47a53107db61b8d90050c06287b425a428f0528d44242a508421acfab"
  }
}
