{
  "module": "M3.5",
  "titre": "Dashboard Admin (KPI Bloc 1 + blocs §11 + parité) — souche (manifeste manquant, livrables P0)",
  "description": "Souche créée en R0b : le dashboard Admin (cartes KPI, blocs graphiques §11, parité 3 rôles) n'avait pas de manifeste alors qu'il porte un P0 (BL-P0-05 KPI à 0 sur enum). deliverables[] transcrit les livrables CDC ; scenarios[]/tests câblés par les lots R4/R20.",
  "_souche": true,
  "scenarios": [],
  "deliverables": [
    {
      "id": "BL-P0-05",
      "ref_cdc": "specs/cdc/01 - Cahier des charges App/11 - Dashboards.md:24",
      "artefact": "packages/plateforme/src/app/api/v1/admin/dashboard/kpi/route.ts",
      "test": "M3.5 / Bloc 1 — N collectes zero_dechet → carte ZD = N (oracle BL-P0-05, pas 0)",
      "statut": "implemented",
      "libelle": "6 compteurs des cartes-actions Bloc 1 filtrent collectes.type sur l'enum réel (zero_dechet/anti_gaspi, plus jamais 'zd'/'ag')"
    },
    {
      "id": "M3.5-chips-collectes-enum",
      "ref_cdc": "specs/cdc/01 - Cahier des charges App/11 - Dashboards.md:24",
      "artefact": "packages/plateforme/src/app/api/v1/admin/collectes/route.ts",
      "test": "M3.5 / chip zd_48h → filtre type=zero_dechet (count 7, pas 0)",
      "statut": "implemented",
      "libelle": "chips prédéfinis de la liste collectes (cibles de clic des cartes Bloc 1) filtrent collectes.type sur l'enum réel (zd_48h/ag_48h/ag_attente_attribution)"
    },
    {
      "id": "BL-P1-PARITE-01",
      "ref_cdc": "specs/cdc/01 - Cahier des charges App/11 - Dashboards.md",
      "artefact": null,
      "test": null,
      "statut": "à-vérifier",
      "libelle": "Blocs §11 manquants — cluster parité 3 rôles"
    },
    {
      "id": "BL-P1-PARITE-02",
      "ref_cdc": "specs/cdc/01 - Cahier des charges App/11 - Dashboards.md",
      "artefact": null,
      "test": null,
      "statut": "à-vérifier",
      "libelle": "Export PDF synthèse (stub « V4 » non descopé)"
    },
    {
      "id": "BL-P2-03",
      "ref_cdc": "specs/cdc/01 - Cahier des charges App/11 - Dashboards.md",
      "artefact": null,
      "test": null,
      "statut": "à-vérifier",
      "libelle": "Dashboard Admin Bloc 2 Revenus"
    },
    {
      "id": "BL-P2-11",
      "ref_cdc": "specs/cdc/01 - Cahier des charges App/11 - Dashboards.md",
      "artefact": null,
      "test": null,
      "statut": "à-vérifier",
      "libelle": "Dashboards : filtres globaux + cartes cliquables (3 rôles)"
    },
    {
      "id": "BL-P2-43",
      "ref_cdc": "specs/cdc/01 - Cahier des charges App/11 - Dashboards.md",
      "artefact": null,
      "test": null,
      "statut": "partial",
      "libelle": "Pré-cochage type collecte depuis dashboard"
    }
  ],
  "cdc_source_hash": {
    "specs/cdc/01 - Cahier des charges App/11 - Dashboards.md": "1d64d72cffde79652a34cbd80f44b1b52a07fc7790bf80b593fe6a483d25aa7e"
  }
}
